batchutils/__init__.py
batchutils/_version.py
batchutils/async_utils.py
batchutils/bash.py
batchutils/combine_tsvs.py
batchutils/tables.py
batchutils-0.1.5.1.dist-info/LICENSE.md
batchutils-0.1.5.1.dist-info/METADATA
batchutils-0.1.5.1.dist-info/WHEEL
batchutils-0.1.5.1.dist-info/top_level.txt
batchutils-0.1.5.1.dist-info/RECORD
