Metadata-Version: 2.1
Name: batchutils
Version: 0.1.5.1
Summary: Methods and functions that support the overall operations of code based on Hail Batch.
Home-page: https://github.com/tarjindersingh/batchutils
Author: Tarjinder Singh
Author-email: tsingh@broadinstitute.org
License: MIT license
Platform: UNKNOWN
Requires-Python: >=3.7
License-File: LICENSE.md
Requires-Dist: autopep8 (==1.5.4)
Requires-Dist: versioneer (>=0.18)
Requires-Dist: logzero (==1.5.0)
Requires-Dist: datatracker (>=0.2.0)
Requires-Dist: hail
